htmler/__init__.py
htmler/base.py
htmler/block.py
htmler/inline.py
tests/__init__.py
tests/test_all.py
htmler-0.1.3.dist-info/LICENSE.md
htmler-0.1.3.dist-info/METADATA
htmler-0.1.3.dist-info/WHEEL
htmler-0.1.3.dist-info/top_level.txt
htmler-0.1.3.dist-info/RECORD
