Metadata-Version: 2.1
Name: htmler
Version: 0.1.3
Summary: A simple HTML generation library
Home-page: https://github.com/ashep/htmler
Author: Oleksandr Shepetko
Author-email: a@shepetko.com
License: UNKNOWN
Download-URL: https://github.com/ashep/htmler/archive/master.zip
Platform: UNKNOWN
Classifier: Development Status :: 5 - Production/Stable
Classifier: Environment :: Web Environment
Classifier: Intended Audience :: Developers
Classifier: License :: OSI Approved :: MIT License
Classifier: Operating System :: OS Independent
Classifier: Programming Language :: Python :: 3.6
Classifier: Programming Language :: Python :: 3.7
Classifier: Programming Language :: Python :: 3.8
Classifier: Topic :: Software Development :: Code Generators
Classifier: Topic :: Software Development :: Libraries :: Python Modules
Classifier: Topic :: Text Processing :: Markup :: HTML
